commondao/__init__.py
commondao/annotation.py
commondao/commondao.py
commondao/error.py
commondao/py.typed
commondao-1.4.2.dist-info/licenses/LICENSE
commondao-1.4.2.dist-info/METADATA
commondao-1.4.2.dist-info/WHEEL
commondao-1.4.2.dist-info/top_level.txt
commondao-1.4.2.dist-info/RECORD
