Metadata-Version: 2.4
Name: commondao
Version: 1.4.2
Summary: Mysql toolkit
Author-email: qorzj <goodhorsezxj@gmail.com>
License: Apache-2.0
Project-URL: homepage, https://github.com/lessweb/commondao
Keywords: mysql
Requires-Python: >=3.10
License-File: LICENSE
Requires-Dist: mysql-connector-python
Requires-Dist: aiomysql
Requires-Dist: cryptography
Requires-Dist: orjson
Requires-Dist: pydantic
Provides-Extra: test
Requires-Dist: flake8; extra == "test"
Requires-Dist: mypy; extra == "test"
Requires-Dist: coverage; extra == "test"
Requires-Dist: pytest; extra == "test"
Requires-Dist: pytest-cov; extra == "test"
Requires-Dist: pytest-mock; extra == "test"
Requires-Dist: pytest-asyncio; extra == "test"
Requires-Dist: types-toml; extra == "test"
Dynamic: license-file
